.coveragerc
LICENSE
MANIFEST.in
README.rst
requirements.txt
setup.cfg
setup.py
docs/Makefile
docs/conf.py
docs/index.rst
docs/modules/activations.rst
docs/modules/data.rst
docs/modules/hyperparameters.rst
docs/modules/init.rst
docs/modules/layers.rst
docs/modules/model.rst
docs/modules/network.rst
docs/modules/objectives.rst
docs/modules/updates.rst
docs/modules/utils.rst
docs/user/installation.rst
docs/user/tutorial.rst
examples/__init__.py
examples/hp_grid_search_example.py
examples/lstm_example.py
examples/mnist_examples.py
examples/model_template.py
examples/networks.py
examples/normalization_example.py
examples/save_and_load_example.py
examples/test.py
examples/updates_examples.py
tests/__init__.py
tests/test_activation.py
tests/test_data.py
tests/test_hyperparameters.py
tests/test_init.py
tests/test_layers.py
tests/test_model.py
tests/test_network.py
tests/test_objectives.py
tests/test_updates.py
tests/test_utils.py
yadll/__init__.py
yadll/activations.py
yadll/data.py
yadll/exceptions.py
yadll/hyperparameters.py
yadll/init.py
yadll/layers.py
yadll/model.py
yadll/network.py
yadll/objectives.py
yadll/updates.py
yadll/utils.py
yadll.egg-info/PKG-INFO
yadll.egg-info/SOURCES.txt
yadll.egg-info/dependency_links.txt
yadll.egg-info/requires.txt
yadll.egg-info/top_level.txt