Metadata-Version: 1.0
Name: yadll
Version: 0.0.1
Summary: Yet Another Deep Learning Lab. Ultra light Deep Learning framework based on Theano
Home-page: https://github.com/pchavanne/yadll
Author: Philippe Chavanne
Author-email: philippe.chavanne@gmail.com
License: MIT
Platform: UNKNOWN
